NPB_data2023/__init__.py
NPB_data2023-0.1.0.dist-info/METADATA
NPB_data2023-0.1.0.dist-info/WHEEL
NPB_data2023-0.1.0.dist-info/top_level.txt
NPB_data2023-0.1.0.dist-info/RECORD
