Metadata-Version: 2.1
Name: NPB-data2023
Version: 0.1.0
Requires-Dist: pandas
